sdev_secure_discord_pu.py
sdev_secure_discord_pu-1.2.dist-info/METADATA
sdev_secure_discord_pu-1.2.dist-info/WHEEL
sdev_secure_discord_pu-1.2.dist-info/top_level.txt
sdev_secure_discord_pu-1.2.dist-info/RECORD
